Workbook

Sheet README
A1: LLM API cost and value model (illustrative exercise, public list prices)
A3: Purpose | B3: Compare cost per task and value across nine LLM API models (three providers x small / mid / flagship tier), then show where the cheapest model is NOT the best-value model once quality and rework are included.
A4: Status | B4: ILLUSTRATIVE. Prices are public list prices read from each provider's official pricing page on 20 Oct 2026. Token counts, volumes, rework costs and ALL success rates are placeholder assumptions, not measurements. This is not real deal experience, and list prices are not negotiated prices.
A5: Core idea | B5: Cost per task = tokens x price, adjusted for caching and batch. Value = what you actually pay per GOOD outcome: expected cost per task = API cost + (1 - success rate) x rework cost. A cheap model that fails often can cost more overall than an expensive one.
A6: Colour legend | B6: Blue text = hardcoded input you can change. Black = formula. Green = link to another sheet. Yellow fill = key assumption to replace with real evidence (success rates, price-basis switch).
A7: How to use | B7: 1) Prices: check the numbers and the post-promo switch (B3). 2) Tasks: edit the three example tasks to match your workload. 3) Quality: replace the placeholder success rates with pilot results. 4) Read Summary.
A8: Getting real numbers cheaply | B8: Token counts: use each provider's token-counting tool on a sample of real inputs (free or near-free) instead of guessing. Success rates: run 30-50 real samples per task per model (small models cost cents), grade each against a written acceptance rubric, record the share that pass. Output tokens: measure on the pilot, since reasoning models can produce many more output tokens than the visible answer.
A9: Placeholder success rates | B9: Set equal for every provider within a tier, so no provider is favoured by the placeholders. Differences between providers only appear once you replace them with measured results.
A10: Simplifications | B10: Cache write cost uses a multiplier on input price (Anthropic 1.25x for 5-minute cache; OpenAI cache-write rate is 1.25x input). Google Flash storage fees per hour are ignored. Cache misses pay the write multiplier. Batch = flat discount from Prices!N and stacks with caching (per provider docs). Prompts assumed under 100k tokens (Haiku 5.5 charges more above that). Tokenizer and reasoning-token differences default to 1.0x and should be measured.
A11: Price-change risk | B11: Google's Gemini 4 Argon (to 30 Nov 2026) and Gemini 3.8 Flash (to 31 Dec 2026) list promotional prices that double afterwards. Switch Prices!B3 to Y to see the effect. A real deal would address this with price protection or a committed rate.
A12: Sources | B12: Anthropic: platform.claude.com/docs/en/about-claude/pricing | OpenAI: developers.openai.com/api/docs/pricing | Google: ai.google.dev/gemini-api/docs/pricing (all read 20 Oct 2026). Verify before relying on any figure.
A13: Seller-side sheets | B13: Seller_Guardrail turns a margin scenario and a margin floor into discount limits (rep / manager / finance) and tests them on 12 simulated deals. Breakeven shows, per task, the rework cost at which a higher model tier pays for itself.
A14: Margin caveat | B14: Gross margin scenarios (40/60/80%) are placeholders. Public estimates for AI vendors vary widely and depend on definition. No provider publishes per-model or per-deal margins. A deal-level margin guardrail is not a statement about any company's overall profit.

Sheet Summary
A1: Summary: cheapest model vs best-value model per task
A2: ILLUSTRATIVE. Driven by placeholder success rates and rework costs (see Quality and Tasks). Replace with measured data before drawing any conclusion.
A4: Task | B4: Cheapest model by API cost (ignores quality) | C4: Its API cost / task | D4: Its success rate | E4: Its expected total cost / task | F4: Best-value model (meets required rate, lowest expected total cost) | G4: Its API cost / task | H4: Its success rate | I4: Its expected total cost / task | J4: Monthly volume | K4: Monthly expected cost: cheapest | L4: Monthly expected cost: best value | M4: Monthly difference (cheapest minus best value) | N4: Same model?
A5: =Tasks!A6 -> T1 Support triage | B5: =INDEX(Calc!D6:D14,MATCH(MIN(Calc!K6:K14),Calc!K6:K14,0)) -> Claude Haiku 5.5 | C5: =MIN(Calc!K6:K14) -> 0.0002211075 | D5: =INDEX(Calc!L6:L14,MATCH(MIN(Calc!K6:K14),Calc!K6:K14,0)) -> 0.88 | E5: =INDEX(Calc!O6:O14,MATCH(MIN(Calc!K6:K14),Calc!K6:K14,0)) -> 0.24022111 | F5: =IF(MIN(Calc!P6:P14)>=1000000000,"None meets required rate",INDEX(Calc!D6:D14,MATCH(MIN(Calc!P6:P14),Calc!P6:P14,0))) -> Gemini 4 Argon | G5: =IF(MIN(Calc!P6:P14)>=1000000000,0,INDEX(Calc!K6:K14,MATCH(MIN(Calc!P6:P14),Calc!P6:P14,0))) -> 0.00428145 | H5: =IF(MIN(Calc!P6:P14)>=1000000000,0,INDEX(Calc!L6:L14,MATCH(MIN(Calc!P6:P14),Calc!P6:P14,0))) -> 0.97 | I5: =IF(MIN(Calc!P6:P14)>=1000000000,0,MIN(Calc!P6:P14)) -> 0.06428145 | J5: =Tasks!G6 -> 200000 | K5: =E5*J5 -> 48044.221 | L5: =I5*J5 -> 12856.29 | M5: =K5-L5 -> 35187.931 | N5: =IF(B5=F5,"Yes","No") -> No
A6: =Tasks!A7 -> T2 Document summary | B6: =INDEX(Calc!D15:D23,MATCH(MIN(Calc!K15:K23),Calc!K15:K23,0)) -> Claude Haiku 5.5 | C6: =MIN(Calc!K15:K23) -> 0.0011675 | D6: =INDEX(Calc!L15:L23,MATCH(MIN(Calc!K15:K23),Calc!K15:K23,0)) -> 0.8 | E6: =INDEX(Calc!O15:O23,MATCH(MIN(Calc!K15:K23),Calc!K15:K23,0)) -> 1.6011675 | F6: =IF(MIN(Calc!P15:P23)>=1000000000,"None meets required rate",INDEX(Calc!D15:D23,MATCH(MIN(Calc!P15:P23),Calc!P15:P23,0))) -> Gemini 4 Argon | G6: =IF(MIN(Calc!P15:P23)>=1000000000,0,INDEX(Calc!K15:K23,MATCH(MIN(Calc!P15:P23),Calc!P15:P23,0))) -> 0.02305 | H6: =IF(MIN(Calc!P15:P23)>=1000000000,0,INDEX(Calc!L15:L23,MATCH(MIN(Calc!P15:P23),Calc!P15:P23,0))) -> 0.95 | I6: =IF(MIN(Calc!P15:P23)>=1000000000,0,MIN(Calc!P15:P23)) -> 0.42305 | J6: =Tasks!G7 -> 5000 | K6: =E6*J6 -> 8005.8375 | L6: =I6*J6 -> 2115.25 | M6: =K6-L6 -> 5890.5875 | N6: =IF(B6=F6,"Yes","No") -> No
A7: =Tasks!A8 -> T3 Complex analysis | B7: =INDEX(Calc!D24:D32,MATCH(MIN(Calc!K24:K32),Calc!K24:K32,0)) -> Claude Haiku 5.5 | C7: =MIN(Calc!K24:K32) -> 0.005446 | D7: =INDEX(Calc!L24:L32,MATCH(MIN(Calc!K24:K32),Calc!K24:K32,0)) -> 0.35 | E7: =INDEX(Calc!O24:O32,MATCH(MIN(Calc!K24:K32),Calc!K24:K32,0)) -> 26.005446 | F7: =IF(MIN(Calc!P24:P32)>=1000000000,"None meets required rate",INDEX(Calc!D24:D32,MATCH(MIN(Calc!P24:P32),Calc!P24:P32,0))) -> Gemini 4 Argon | G7: =IF(MIN(Calc!P24:P32)>=1000000000,0,INDEX(Calc!K24:K32,MATCH(MIN(Calc!P24:P32),Calc!P24:P32,0))) -> 0.10276 | H7: =IF(MIN(Calc!P24:P32)>=1000000000,0,INDEX(Calc!L24:L32,MATCH(MIN(Calc!P24:P32),Calc!P24:P32,0))) -> 0.88 | I7: =IF(MIN(Calc!P24:P32)>=1000000000,0,MIN(Calc!P24:P32)) -> 4.90276 | J7: =Tasks!G8 -> 1000 | K7: =E7*J7 -> 26005.446 | L7: =I7*J7 -> 4902.76 | M7: =K7-L7 -> 21102.686 | N7: =IF(B7=F7,"Yes","No") -> No
A9: Reading it: where 'Same model?' is No, the cheapest model on API cost is not the best value once failed outputs are priced in. A positive monthly difference means the best-value choice saves money overall despite a higher API bill.
A10: Not modelled: output quality beyond pass/fail, latency, rate limits, support terms, data residency premium (+10% on some providers), negotiated discounts, and price changes after the promo periods unless Prices!B3 is set to Y.

Sheet Seller_Guardrail
A1: Seller-side: discount limits and approval guardrail (ILLUSTRATIVE)
A2: Gross margins are scenario assumptions, not company data: public estimates for AI vendors vary widely with how gross margin is defined. Deals are simulated. This is a deal-level (gross margin) guardrail; it says nothing about a company's overall profit.
A4: Selected scenario | B4: Base
A6: Parameter | B6: Low | C6: Base | D6: High | E6: Selected | F6: Notes
A7: Gross margin before discount (assumption) | B7: 0.4 | C7: 0.6 | D7: 0.8 | E7: =INDEX(B7:D7,MATCH($B$4,$B$6:$D$6,0)) -> 0.6 | F7: Placeholder scenarios, not company figures.
A8: Gross margin floor after discount | B8: 0.25 | C8: =$B$8 -> 0.25 | D8: =$B$8 -> 0.25 | E8: =INDEX(B8:D8,MATCH($B$4,$B$6:$D$6,0)) -> 0.25 | F8: Lowest gross margin you accept on any deal. Set once in B8.
A9: Max discount before breaching the floor | B9: =1-(1-B7)/(1-B8) -> 0.2 | C9: =1-(1-C7)/(1-C8) -> 0.46666667 | D9: =1-(1-D7)/(1-D8) -> 0.73333333 | E9: =INDEX(B9:D9,MATCH($B$4,$B$6:$D$6,0)) -> 0.46666667 | F9: d = 1 - (1 - margin) / (1 - floor). Cost is fixed, price falls with discount.
A10: Rep authority (share of max discount) | B10: 0.4 | C10: =$B$10 -> 0.4 | D10: =$B$10 -> 0.4 | E10: =INDEX(B10:D10,MATCH($B$4,$B$6:$D$6,0)) -> 0.4 | F10: Design choice: the trade-off between speed and margin protection.
A11: Manager authority (share of max discount) | B11: 0.75 | C11: =$B$11 -> 0.75 | D11: =$B$11 -> 0.75 | E11: =INDEX(B11:D11,MATCH($B$4,$B$6:$D$6,0)) -> 0.75
A12: Rounding step for limits | B12: 0.05 | C12: =$B$12 -> 0.05 | D12: =$B$12 -> 0.05 | E12: =INDEX(B12:D12,MATCH($B$4,$B$6:$D$6,0)) -> 0.05
A13: Rep can approve up to | B13: =ROUNDDOWN(B10*B9/B12,0)*B12 -> 0.05 | C13: =ROUNDDOWN(C10*C9/C12,0)*C12 -> 0.15 | D13: =ROUNDDOWN(D10*D9/D12,0)*D12 -> 0.25 | E13: =INDEX(B13:D13,MATCH($B$4,$B$6:$D$6,0)) -> 0.15 | F13: Limits shift with the margin scenario: check the guardrail holds under Low.
A14: Manager can approve up to | B14: =ROUNDDOWN(B11*B9/B12,0)*B12 -> 0.15 | C14: =ROUNDDOWN(C11*C9/C12,0)*C12 -> 0.35 | D14: =ROUNDDOWN(D11*D9/D12,0)*D12 -> 0.55 | E14: =INDEX(B14:D14,MATCH($B$4,$B$6:$D$6,0)) -> 0.35
A15: Finance can approve up to (above this = exception) | B15: =ROUNDDOWN(B9/B12,0)*B12 -> 0.2 | C15: =ROUNDDOWN(C9/C12,0)*C12 -> 0.45 | D15: =ROUNDDOWN(D9/D12,0)*D12 -> 0.7 | E15: =INDEX(B15:D15,MATCH($B$4,$B$6:$D$6,0)) -> 0.45
A17: Simulated deals (hypothetical, not real customers)
A19: Deal ID | B19: Monthly list spend ($) | C19: Term (months) | D19: Requested discount | E19: List TCV ($) | F19: Net TCV ($) | G19: Discount given ($) | H19: Gross margin after discount | I19: Gross profit over term ($) | J19: Approval needed | K19: Below margin floor?
A20: D01 | B20: 5000 | C20: 12 | D20: 0.05 | E20: =B20*C20 -> 60000 | F20: =E20*(1-D20) -> 57000 | G20: =E20-F20 -> 3000 | H20: =1-(1-$E$7)/(1-D20) -> 0.57894737 | I20: =F20-E20*(1-$E$7) -> 33000 | J20: =IF(D20<=$E$13,"Rep",IF(D20<=$E$14,"Manager",IF(D20<=$E$15,"Finance","Exception (below floor)"))) -> Rep | K20: =IF(H20<$E$8,"Yes","No") -> No
A21: D02 | B21: 12000 | C21: 12 | D21: 0.1 | E21: =B21*C21 -> 144000 | F21: =E21*(1-D21) -> 129600 | G21: =E21-F21 -> 14400 | H21: =1-(1-$E$7)/(1-D21) -> 0.55555556 | I21: =F21-E21*(1-$E$7) -> 72000 | J21: =IF(D21<=$E$13,"Rep",IF(D21<=$E$14,"Manager",IF(D21<=$E$15,"Finance","Exception (below floor)"))) -> Rep | K21: =IF(H21<$E$8,"Yes","No") -> No
A22: D03 | B22: 25000 | C22: 12 | D22: 0.15 | E22: =B22*C22 -> 300000 | F22: =E22*(1-D22) -> 255000 | G22: =E22-F22 -> 45000 | H22: =1-(1-$E$7)/(1-D22) -> 0.52941176 | I22: =F22-E22*(1-$E$7) -> 135000 | J22: =IF(D22<=$E$13,"Rep",IF(D22<=$E$14,"Manager",IF(D22<=$E$15,"Finance","Exception (below floor)"))) -> Rep | K22: =IF(H22<$E$8,"Yes","No") -> No
A23: D04 | B23: 40000 | C23: 24 | D23: 0.2 | E23: =B23*C23 -> 960000 | F23: =E23*(1-D23) -> 768000 | G23: =E23-F23 -> 192000 | H23: =1-(1-$E$7)/(1-D23) -> 0.5 | I23: =F23-E23*(1-$E$7) -> 384000 | J23: =IF(D23<=$E$13,"Rep",IF(D23<=$E$14,"Manager",IF(D23<=$E$15,"Finance","Exception (below floor)"))) -> Manager | K23: =IF(H23<$E$8,"Yes","No") -> No
A24: D05 | B24: 60000 | C24: 24 | D24: 0.25 | E24: =B24*C24 -> 1440000 | F24: =E24*(1-D24) -> 1080000 | G24: =E24-F24 -> 360000 | H24: =1-(1-$E$7)/(1-D24) -> 0.46666667 | I24: =F24-E24*(1-$E$7) -> 504000 | J24: =IF(D24<=$E$13,"Rep",IF(D24<=$E$14,"Manager",IF(D24<=$E$15,"Finance","Exception (below floor)"))) -> Manager | K24: =IF(H24<$E$8,"Yes","No") -> No
A25: D06 | B25: 80000 | C25: 36 | D25: 0.3 | E25: =B25*C25 -> 2880000 | F25: =E25*(1-D25) -> 2016000 | G25: =E25-F25 -> 864000 | H25: =1-(1-$E$7)/(1-D25) -> 0.42857143 | I25: =F25-E25*(1-$E$7) -> 864000 | J25: =IF(D25<=$E$13,"Rep",IF(D25<=$E$14,"Manager",IF(D25<=$E$15,"Finance","Exception (below floor)"))) -> Manager | K25: =IF(H25<$E$8,"Yes","No") -> No
A26: D07 | B26: 120000 | C26: 36 | D26: 0.35 | E26: =B26*C26 -> 4320000 | F26: =E26*(1-D26) -> 2808000 | G26: =E26-F26 -> 1512000 | H26: =1-(1-$E$7)/(1-D26) -> 0.38461538 | I26: =F26-E26*(1-$E$7) -> 1080000 | J26: =IF(D26<=$E$13,"Rep",IF(D26<=$E$14,"Manager",IF(D26<=$E$15,"Finance","Exception (below floor)"))) -> Manager | K26: =IF(H26<$E$8,"Yes","No") -> No
A27: D08 | B27: 8000 | C27: 12 | D27: 0.12 | E27: =B27*C27 -> 96000 | F27: =E27*(1-D27) -> 84480 | G27: =E27-F27 -> 11520 | H27: =1-(1-$E$7)/(1-D27) -> 0.54545455 | I27: =F27-E27*(1-$E$7) -> 46080 | J27: =IF(D27<=$E$13,"Rep",IF(D27<=$E$14,"Manager",IF(D27<=$E$15,"Finance","Exception (below floor)"))) -> Rep | K27: =IF(H27<$E$8,"Yes","No") -> No
A28: D09 | B28: 200000 | C28: 36 | D28: 0.4 | E28: =B28*C28 -> 7200000 | F28: =E28*(1-D28) -> 4320000 | G28: =E28-F28 -> 2880000 | H28: =1-(1-$E$7)/(1-D28) -> 0.33333333 | I28: =F28-E28*(1-$E$7) -> 1440000 | J28: =IF(D28<=$E$13,"Rep",IF(D28<=$E$14,"Manager",IF(D28<=$E$15,"Finance","Exception (below floor)"))) -> Finance | K28: =IF(H28<$E$8,"Yes","No") -> No
A29: D10 | B29: 15000 | C29: 24 | D29: 0.18 | E29: =B29*C29 -> 360000 | F29: =E29*(1-D29) -> 295200 | G29: =E29-F29 -> 64800 | H29: =1-(1-$E$7)/(1-D29) -> 0.51219512 | I29: =F29-E29*(1-$E$7) -> 151200 | J29: =IF(D29<=$E$13,"Rep",IF(D29<=$E$14,"Manager",IF(D29<=$E$15,"Finance","Exception (below floor)"))) -> Manager | K29: =IF(H29<$E$8,"Yes","No") -> No
A30: D11 | B30: 300000 | C30: 36 | D30: 0.45 | E30: =B30*C30 -> 10800000 | F30: =E30*(1-D30) -> 5940000 | G30: =E30-F30 -> 4860000 | H30: =1-(1-$E$7)/(1-D30) -> 0.27272727 | I30: =F30-E30*(1-$E$7) -> 1620000 | J30: =IF(D30<=$E$13,"Rep",IF(D30<=$E$14,"Manager",IF(D30<=$E$15,"Finance","Exception (below floor)"))) -> Finance | K30: =IF(H30<$E$8,"Yes","No") -> No
A31: D12 | B31: 3000 | C31: 12 | D31: 0 | E31: =B31*C31 -> 36000 | F31: =E31*(1-D31) -> 36000 | G31: =E31-F31 -> 0 | H31: =1-(1-$E$7)/(1-D31) -> 0.6 | I31: =F31-E31*(1-$E$7) -> 21600 | J31: =IF(D31<=$E$13,"Rep",IF(D31<=$E$14,"Manager",IF(D31<=$E$15,"Finance","Exception (below floor)"))) -> Rep | K31: =IF(H31<$E$8,"Yes","No") -> No
A34: Approval load and margin protected (selected scenario)
A35: Approval level | B35: Deals | C35: Share of deals | D35: Net TCV ($) | E35: Discount given ($) | F35: Gross profit over term ($) | G35: Blended gross margin
A36: Rep | B36: =COUNTIF($J$20:$J$31,A36) -> 5 | C36: =B36/$B$40 -> 0.41666667 | D36: =SUMIF($J$20:$J$31,A36,$F$20:$F$31) -> 562080 | E36: =SUMIF($J$20:$J$31,A36,$G$20:$G$31) -> 73920 | F36: =SUMIF($J$20:$J$31,A36,$I$20:$I$31) -> 307680 | G36: =IF(D36>0,F36/D36,0) -> 0.54739539
A37: Manager | B37: =COUNTIF($J$20:$J$31,A37) -> 5 | C37: =B37/$B$40 -> 0.41666667 | D37: =SUMIF($J$20:$J$31,A37,$F$20:$F$31) -> 6967200 | E37: =SUMIF($J$20:$J$31,A37,$G$20:$G$31) -> 2992800 | F37: =SUMIF($J$20:$J$31,A37,$I$20:$I$31) -> 2983200 | G37: =IF(D37>0,F37/D37,0) -> 0.42817775
A38: Finance | B38: =COUNTIF($J$20:$J$31,A38) -> 2 | C38: =B38/$B$40 -> 0.16666667 | D38: =SUMIF($J$20:$J$31,A38,$F$20:$F$31) -> 10260000 | E38: =SUMIF($J$20:$J$31,A38,$G$20:$G$31) -> 7740000 | F38: =SUMIF($J$20:$J$31,A38,$I$20:$I$31) -> 3060000 | G38: =IF(D38>0,F38/D38,0) -> 0.29824561
A39: Exception (below floor) | B39: =COUNTIF($J$20:$J$31,A39) -> 0 | C39: =B39/$B$40 -> 0 | D39: =SUMIF($J$20:$J$31,A39,$F$20:$F$31) -> 0 | E39: =SUMIF($J$20:$J$31,A39,$G$20:$G$31) -> 0 | F39: =SUMIF($J$20:$J$31,A39,$I$20:$I$31) -> 0 | G39: =IF(D39>0,F39/D39,0) -> 0
A40: Total | B40: =SUM(B36:B39) -> 12 | C40: =SUM(C36:C39) -> 1 | D40: =SUM(D36:D39) -> 17789280 | E40: =SUM(E36:E39) -> 10806720 | F40: =SUM(F36:F39) -> 6350880 | G40: =IF(D40>0,F40/D40,0) -> 0.35700602
A42: Reading it: a tighter guardrail (lower limits) sends more deals to managers and finance, which protects margin but adds delay. A looser one speeds deals up but risks margin. Flip B4 to Low to test the stricter case.

Sheet Breakeven
A1: Buyer-side break-even: when does a higher tier pay for itself? (ILLUSTRATIVE)
A2: Tier averages across the three providers, so no provider is favoured. Break-even rework cost = extra API cost / success-rate gain. If your real rework cost per failed task is above this, the higher tier is cheaper overall. Success rates are placeholders.
A5: Task | B5: From tier | C5: To tier | D5: Avg API cost / task (from) | E5: Avg API cost / task (to) | F5: Avg success (from) | G5: Avg success (to) | H5: Success gain | I5: Extra API cost / task | J5: Break-even rework cost ($) | K5: Assumed rework cost ($) | L5: Does the higher tier pay off?
A6: =Tasks!A6 -> T1 Support triage | B6: Small | C6: Mid | D6: =AVERAGEIFS(Calc!$K$6:$K$32,Calc!$A$6:$A$32,$A6,Calc!$C$6:$C$32,$B6) -> 0.000466 | E6: =AVERAGEIFS(Calc!$K$6:$K$32,Calc!$A$6:$A$32,$A6,Calc!$C$6:$C$32,$C6) -> 0.0034342875 | F6: =AVERAGEIFS(Calc!$L$6:$L$32,Calc!$A$6:$A$32,$A6,Calc!$C$6:$C$32,$B6) -> 0.88 | G6: =AVERAGEIFS(Calc!$L$6:$L$32,Calc!$A$6:$A$32,$A6,Calc!$C$6:$C$32,$C6) -> 0.95 | H6: =G6-F6 -> 0.07 | I6: =E6-D6 -> 0.0029682875 | J6: =IF(H6>0,I6/H6,"n/a") -> 0.042404107 | K6: =Tasks!I6 -> 2 | L6: =IF(H6<=0,"No quality gain",IF(K6>=J6,"Yes","No")) -> Yes
A7: =Tasks!A6 -> T1 Support triage | B7: Mid | C7: Flagship | D7: =AVERAGEIFS(Calc!$K$6:$K$32,Calc!$A$6:$A$32,$A7,Calc!$C$6:$C$32,$B7) -> 0.0034342875 | E7: =AVERAGEIFS(Calc!$K$6:$K$32,Calc!$A$6:$A$32,$A7,Calc!$C$6:$C$32,$C7) -> 0.015941525 | F7: =AVERAGEIFS(Calc!$L$6:$L$32,Calc!$A$6:$A$32,$A7,Calc!$C$6:$C$32,$B7) -> 0.95 | G7: =AVERAGEIFS(Calc!$L$6:$L$32,Calc!$A$6:$A$32,$A7,Calc!$C$6:$C$32,$C7) -> 0.97 | H7: =G7-F7 -> 0.02 | I7: =E7-D7 -> 0.012507238 | J7: =IF(H7>0,I7/H7,"n/a") -> 0.62536187 | K7: =Tasks!I6 -> 2 | L7: =IF(H7<=0,"No quality gain",IF(K7>=J7,"Yes","No")) -> Yes
A8: =Tasks!A7 -> T2 Document summary | B8: Small | C8: Mid | D8: =AVERAGEIFS(Calc!$K$6:$K$32,Calc!$A$6:$A$32,$A8,Calc!$C$6:$C$32,$B8) -> 0.0020666667 | E8: =AVERAGEIFS(Calc!$K$6:$K$32,Calc!$A$6:$A$32,$A8,Calc!$C$6:$C$32,$C8) -> 0.018420833 | F8: =AVERAGEIFS(Calc!$L$6:$L$32,Calc!$A$6:$A$32,$A8,Calc!$C$6:$C$32,$B8) -> 0.8 | G8: =AVERAGEIFS(Calc!$L$6:$L$32,Calc!$A$6:$A$32,$A8,Calc!$C$6:$C$32,$C8) -> 0.92 | H8: =G8-F8 -> 0.12 | I8: =E8-D8 -> 0.016354167 | J8: =IF(H8>0,I8/H8,"n/a") -> 0.13628472 | K8: =Tasks!I7 -> 8 | L8: =IF(H8<=0,"No quality gain",IF(K8>=J8,"Yes","No")) -> Yes
A9: =Tasks!A7 -> T2 Document summary | B9: Mid | C9: Flagship | D9: =AVERAGEIFS(Calc!$K$6:$K$32,Calc!$A$6:$A$32,$A9,Calc!$C$6:$C$32,$B9) -> 0.018420833 | E9: =AVERAGEIFS(Calc!$K$6:$K$32,Calc!$A$6:$A$32,$A9,Calc!$C$6:$C$32,$C9) -> 0.085391667 | F9: =AVERAGEIFS(Calc!$L$6:$L$32,Calc!$A$6:$A$32,$A9,Calc!$C$6:$C$32,$B9) -> 0.92 | G9: =AVERAGEIFS(Calc!$L$6:$L$32,Calc!$A$6:$A$32,$A9,Calc!$C$6:$C$32,$C9) -> 0.95 | H9: =G9-F9 -> 0.03 | I9: =E9-D9 -> 0.066970833 | J9: =IF(H9>0,I9/H9,"n/a") -> 2.2323611 | K9: =Tasks!I7 -> 8 | L9: =IF(H9<=0,"No quality gain",IF(K9>=J9,"Yes","No")) -> Yes
A10: =Tasks!A8 -> T3 Complex analysis | B10: Small | C10: Mid | D10: =AVERAGEIFS(Calc!$K$6:$K$32,Calc!$A$6:$A$32,$A10,Calc!$C$6:$C$32,$B10) -> 0.010866667 | E10: =AVERAGEIFS(Calc!$K$6:$K$32,Calc!$A$6:$A$32,$A10,Calc!$C$6:$C$32,$C10) -> 0.084396667 | F10: =AVERAGEIFS(Calc!$L$6:$L$32,Calc!$A$6:$A$32,$A10,Calc!$C$6:$C$32,$B10) -> 0.35 | G10: =AVERAGEIFS(Calc!$L$6:$L$32,Calc!$A$6:$A$32,$A10,Calc!$C$6:$C$32,$C10) -> 0.7 | H10: =G10-F10 -> 0.35 | I10: =E10-D10 -> 0.07353 | J10: =IF(H10>0,I10/H10,"n/a") -> 0.21008571 | K10: =Tasks!I8 -> 40 | L10: =IF(H10<=0,"No quality gain",IF(K10>=J10,"Yes","No")) -> Yes
A11: =Tasks!A8 -> T3 Complex analysis | B11: Mid | C11: Flagship | D11: =AVERAGEIFS(Calc!$K$6:$K$32,Calc!$A$6:$A$32,$A11,Calc!$C$6:$C$32,$B11) -> 0.084396667 | E11: =AVERAGEIFS(Calc!$K$6:$K$32,Calc!$A$6:$A$32,$A11,Calc!$C$6:$C$32,$C11) -> 0.39242 | F11: =AVERAGEIFS(Calc!$L$6:$L$32,Calc!$A$6:$A$32,$A11,Calc!$C$6:$C$32,$B11) -> 0.7 | G11: =AVERAGEIFS(Calc!$L$6:$L$32,Calc!$A$6:$A$32,$A11,Calc!$C$6:$C$32,$C11) -> 0.88 | H11: =G11-F11 -> 0.18 | I11: =E11-D11 -> 0.30802333 | J11: =IF(H11>0,I11/H11,"n/a") -> 1.7112407 | K11: =Tasks!I8 -> 40 | L11: =IF(H11<=0,"No quality gain",IF(K11>=J11,"Yes","No")) -> Yes

Sheet Prices
A1: List prices, USD per 1M tokens (read 20 Oct 2026)
A3: Use post-promo prices? (Y/N) | B3: N | C3: Y applies the higher prices Google has announced for after its promotional periods.
A5: Provider | B5: Tier | C5: Model | D5: Current input | E5: Current output | F5: Current cached-read | G5: Post-promo input | H5: Post-promo output | I5: Post-promo cached-read | J5: Effective input | K5: Effective output | L5: Effective cached-read | M5: Cache write multiplier (x input) | N5: Batch discount | O5: Tokenizer multiplier | P5: Output (reasoning) multiplier | Q5: Source / notes
A6: Anthropic | B6: Small | C6: Claude Haiku 5.5 | D6: 0.1 | E6: 0.5 | F6: 0.01 | G6: =D6 -> 0.1 | H6: =E6 -> 0.5 | I6: =F6 -> 0.01 | J6: =IF($B$3="Y",G6,D6) -> 0.1 | K6: =IF($B$3="Y",H6,E6) -> 0.5 | L6: =IF($B$3="Y",I6,F6) -> 0.01 | M6: 1.25 | N6: 0.5 | O6: 1 | P6: 1 | Q6: Anthropic pricing page. Prompts up to 100k tokens; 5-min cache write 1.25x.
A7: Anthropic | B7: Mid | C7: Claude Sonnet 5.5 | D7: 2 | E7: 10 | F7: 0.1 | G7: =D7 -> 2 | H7: =E7 -> 10 | I7: =F7 -> 0.1 | J7: =IF($B$3="Y",G7,D7) -> 2 | K7: =IF($B$3="Y",H7,E7) -> 10 | L7: =IF($B$3="Y",I7,F7) -> 0.1 | M7: 1.25 | N7: 0.5 | O7: 1 | P7: 1 | Q7: Anthropic pricing page. Cache hit 0.05x input.
A8: Anthropic | B8: Flagship | C8: Claude Fable 5.1 | D8: 10 | E8: 50 | F8: 0.25 | G8: =D8 -> 10 | H8: =E8 -> 50 | I8: =F8 -> 0.25 | J8: =IF($B$3="Y",G8,D8) -> 10 | K8: =IF($B$3="Y",H8,E8) -> 50 | L8: =IF($B$3="Y",I8,F8) -> 0.25 | M8: 1.25 | N8: 0.5 | O8: 1 | P8: 1 | Q8: Anthropic pricing page. Cache hit 0.025x input. Opus 5.5 ($4/$20) not modelled.
A9: OpenAI | B9: Small | C9: gpt-6-luna | D9: 0.1 | E9: 0.5 | F9: 0.01 | G9: =D9 -> 0.1 | H9: =E9 -> 0.5 | I9: =F9 -> 0.01 | J9: =IF($B$3="Y",G9,D9) -> 0.1 | K9: =IF($B$3="Y",H9,E9) -> 0.5 | L9: =IF($B$3="Y",I9,F9) -> 0.01 | M9: 1.25 | N9: 0.5 | O9: 1 | P9: 1 | Q9: OpenAI pricing page, short-context rates. Cache write $0.125.
A10: OpenAI | B10: Mid | C10: gpt-6.1-sol | D10: 2 | E10: 10 | F10: 0.1 | G10: =D10 -> 2 | H10: =E10 -> 10 | I10: =F10 -> 0.1 | J10: =IF($B$3="Y",G10,D10) -> 2 | K10: =IF($B$3="Y",H10,E10) -> 10 | L10: =IF($B$3="Y",I10,F10) -> 0.1 | M10: 1.25 | N10: 0.5 | O10: 1 | P10: 1 | Q10: OpenAI pricing page, short-context rates. Cache write $2.50.
A11: OpenAI | B11: Flagship | C11: gpt-6-astra | D11: 10 | E11: 50 | F11: 1 | G11: =D11 -> 10 | H11: =E11 -> 50 | I11: =F11 -> 1 | J11: =IF($B$3="Y",G11,D11) -> 10 | K11: =IF($B$3="Y",H11,E11) -> 50 | L11: =IF($B$3="Y",I11,F11) -> 1 | M11: 1.25 | N11: 0.5 | O11: 1 | P11: 1 | Q11: OpenAI pricing page, short-context rates. Cache write $12.50.
A12: Google | B12: Small | C12: Gemini 3.5 Flash-Lite | D12: 0.3 | E12: 2.5 | F12: 0.03 | G12: =D12 -> 0.3 | H12: =E12 -> 2.5 | I12: =F12 -> 0.03 | J12: =IF($B$3="Y",G12,D12) -> 0.3 | K12: =IF($B$3="Y",H12,E12) -> 2.5 | L12: =IF($B$3="Y",I12,F12) -> 0.03 | M12: 1 | N12: 0.5 | O12: 1 | P12: 1 | Q12: Google pricing page. Storage fee ($1/M tokens/hour) ignored.
A13: Google | B13: Mid | C13: Gemini 3.8 Flash | D13: 0.75 | E13: 3.75 | F13: 0.075 | G13: 1.5 | H13: 7.5 | I13: 0.15 | J13: =IF($B$3="Y",G13,D13) -> 0.75 | K13: =IF($B$3="Y",H13,E13) -> 3.75 | L13: =IF($B$3="Y",I13,F13) -> 0.075 | M13: 1 | N13: 0.5 | O13: 1 | P13: 1 | Q13: Google pricing page. Promo to 31 Dec 2026, doubles from 1 Jan 2027. Storage fee ($0.50/M tokens/hour) ignored.
A14: Google | B14: Flagship | C14: Gemini 4 Argon | D14: 2 | E14: 10 | F14: 0.1 | G14: 4 | H14: 20 | I14: 0.2 | J14: =IF($B$3="Y",G14,D14) -> 2 | K14: =IF($B$3="Y",H14,E14) -> 10 | L14: =IF($B$3="Y",I14,F14) -> 0.1 | M14: 1 | N14: 0.5 | O14: 1 | P14: 1 | Q14: Google pricing page. Promo to 30 Nov 2026, doubles from 1 Dec 2026. Implicit caching only.
A16: Tokenizer and output multipliers default to 1.0x (yellow). Measure them on your own samples; Anthropic notes its newer tokenizer produces ~30% more tokens than its older one, but the cross-provider difference is not published.

Sheet Tasks
A1: Example tasks (placeholder assumptions: replace with your own workload)
A5: Task | B5: Description | C5: Input tokens per task | D5: Output tokens per task | E5: Cacheable share of input | F5: Cache hit rate on cacheable part | G5: Monthly volume (tasks) | H5: Batch allowed? (Y/N) | I5: Rework cost per failed task ($) | J5: Required success rate
A6: T1 Support triage | B6: Classify a customer message and draft a reply; real-time, repeated policy prompt. | C6: 1500 | D6: 300 | E6: 0.67 | F6: 0.9 | G6: 200000 | H6: N | I6: 2 | J6: 0.9
A7: T2 Document summary | B7: Summarise a long document overnight; batch is acceptable. | C7: 20000 | D7: 800 | E7: 0.1 | F7: 0.5 | G7: 5000 | H7: Y | I7: 8 | J7: 0.85
A8: T3 Complex analysis | B8: Multi-step analysis or coding task with large shared context; interactive. | C8: 40000 | D8: 6000 | E8: 0.7 | F8: 0.7 | G8: 1000 | H8: N | I8: 40 | J8: 0.8
A10: Rework cost = what a failed output costs you (human fix, redo, customer impact). It is the most influential assumption for value: test a low and a high figure.
A11: Required success rate = the minimum share of outputs that must pass your acceptance rubric. Models below it are excluded from 'best value'.

Sheet Quality
A1: Success rate by model and task (PLACEHOLDERS: replace with pilot results)
A3: Success rate = share of outputs that meet your written acceptance rubric. Values below are illustrative and identical across providers within a tier; they are not benchmark results.
A5: Provider | B5: Tier | C5: Model | D5: =Tasks!A6 -> T1 Support triage | E5: =Tasks!A7 -> T2 Document summary | F5: =Tasks!A8 -> T3 Complex analysis
A6: =Prices!A6 -> Anthropic | B6: =Prices!B6 -> Small | C6: =Prices!C6 -> Claude Haiku 5.5 | D6: 0.88 | E6: 0.8 | F6: 0.35
A7: =Prices!A7 -> Anthropic | B7: =Prices!B7 -> Mid | C7: =Prices!C7 -> Claude Sonnet 5.5 | D7: 0.95 | E7: 0.92 | F7: 0.7
A8: =Prices!A8 -> Anthropic | B8: =Prices!B8 -> Flagship | C8: =Prices!C8 -> Claude Fable 5.1 | D8: 0.97 | E8: 0.95 | F8: 0.88
A9: =Prices!A9 -> OpenAI | B9: =Prices!B9 -> Small | C9: =Prices!C9 -> gpt-6-luna | D9: 0.88 | E9: 0.8 | F9: 0.35
A10: =Prices!A10 -> OpenAI | B10: =Prices!B10 -> Mid | C10: =Prices!C10 -> gpt-6.1-sol | D10: 0.95 | E10: 0.92 | F10: 0.7
A11: =Prices!A11 -> OpenAI | B11: =Prices!B11 -> Flagship | C11: =Prices!C11 -> gpt-6-astra | D11: 0.97 | E11: 0.95 | F11: 0.88
A12: =Prices!A12 -> Google | B12: =Prices!B12 -> Small | C12: =Prices!C12 -> Gemini 3.5 Flash-Lite | D12: 0.88 | E12: 0.8 | F12: 0.35
A13: =Prices!A13 -> Google | B13: =Prices!B13 -> Mid | C13: =Prices!C13 -> Gemini 3.8 Flash | D13: 0.95 | E13: 0.92 | F13: 0.7
A14: =Prices!A14 -> Google | B14: =Prices!B14 -> Flagship | C14: =Prices!C14 -> Gemini 4 Argon | D14: 0.97 | E14: 0.95 | F14: 0.88

Sheet Calc
A1: Cost and value per task (all formulas)
A2: Costs in USD. Batch+Cache = cached cost x (1 - batch discount). Cheapest feasible respects the task's 'Batch allowed?' flag.
A5: Task | B5: Provider | C5: Tier | D5: Model | E5: Input tokens (adj.) | F5: Output tokens (adj.) | G5: List cost / task | H5: Cached cost / task | I5: Batch cost / task | J5: Batch + cached / task | K5: Cheapest feasible API cost / task | L5: Success rate | M5: Meets required rate? | N5: API cost per successful task | O5: Expected total cost / task (incl. rework) | P5: Helper: value rank (excludes failing models) | Q5: Monthly API cost | R5: Monthly expected total cost
A6: =Tasks!A6 -> T1 Support triage | B6: =Prices!A6 -> Anthropic | C6: =Prices!B6 -> Small | D6: =Prices!C6 -> Claude Haiku 5.5 | E6: =Tasks!C6*Prices!O6 -> 1500 | F6: =Tasks!D6*Prices!O6*Prices!P6 -> 300 | G6: =(E6*Prices!J6+F6*Prices!K6)/1000000 -> 0.0003 | H6: =(E6*(1-Tasks!E6)*Prices!J6+E6*Tasks!E6*(Tasks!F6*Prices!L6+(1-Tasks!F6)*Prices!J6*Prices!M6)+F6*Prices!K6)/1000000 -> 0.0002211075 | I6: =G6*(1-Prices!N6) -> 0.00015 | J6: =H6*(1-Prices!N6) -> 0.00011055375 | K6: =IF(Tasks!H6="Y",MIN(G6:J6),MIN(G6:H6)) -> 0.0002211075 | L6: =Quality!D6 -> 0.88 | M6: =IF(L6>=Tasks!J6,"Yes","No") -> No | N6: =IF(L6>0,K6/L6,0) -> 0.00025125852 | O6: =K6+(1-L6)*Tasks!I6 -> 0.24022111 | P6: =IF(M6="Yes",O6,1000000000) -> 1000000000 | Q6: =K6*Tasks!G6 -> 44.2215 | R6: =O6*Tasks!G6 -> 48044.221
A7: =Tasks!A6 -> T1 Support triage | B7: =Prices!A7 -> Anthropic | C7: =Prices!B7 -> Mid | D7: =Prices!C7 -> Claude Sonnet 5.5 | E7: =Tasks!C6*Prices!O7 -> 1500 | F7: =Tasks!D6*Prices!O7*Prices!P7 -> 300 | G7: =(E7*Prices!J7+F7*Prices!K7)/1000000 -> 0.006 | H7: =(E7*(1-Tasks!E6)*Prices!J7+E7*Tasks!E6*(Tasks!F6*Prices!L7+(1-Tasks!F6)*Prices!J7*Prices!M7)+F7*Prices!K7)/1000000 -> 0.0043317 | I7: =G7*(1-Prices!N7) -> 0.003 | J7: =H7*(1-Prices!N7) -> 0.00216585 | K7: =IF(Tasks!H6="Y",MIN(G7:J7),MIN(G7:H7)) -> 0.0043317 | L7: =Quality!D7 -> 0.95 | M7: =IF(L7>=Tasks!J6,"Yes","No") -> Yes | N7: =IF(L7>0,K7/L7,0) -> 0.0045596842 | O7: =K7+(1-L7)*Tasks!I6 -> 0.1043317 | P7: =IF(M7="Yes",O7,1000000000) -> 0.1043317 | Q7: =K7*Tasks!G6 -> 866.34 | R7: =O7*Tasks!G6 -> 20866.34
A8: =Tasks!A6 -> T1 Support triage | B8: =Prices!A8 -> Anthropic | C8: =Prices!B8 -> Flagship | D8: =Prices!C8 -> Claude Fable 5.1 | E8: =Tasks!C6*Prices!O8 -> 1500 | F8: =Tasks!D6*Prices!O8*Prices!P8 -> 300 | G8: =(E8*Prices!J8+F8*Prices!K8)/1000000 -> 0.03 | H8: =(E8*(1-Tasks!E6)*Prices!J8+E8*Tasks!E6*(Tasks!F6*Prices!L8+(1-Tasks!F6)*Prices!J8*Prices!M8)+F8*Prices!K8)/1000000 -> 0.021432375 | I8: =G8*(1-Prices!N8) -> 0.015 | J8: =H8*(1-Prices!N8) -> 0.010716188 | K8: =IF(Tasks!H6="Y",MIN(G8:J8),MIN(G8:H8)) -> 0.021432375 | L8: =Quality!D8 -> 0.97 | M8: =IF(L8>=Tasks!J6,"Yes","No") -> Yes | N8: =IF(L8>0,K8/L8,0) -> 0.022095232 | O8: =K8+(1-L8)*Tasks!I6 -> 0.081432375 | P8: =IF(M8="Yes",O8,1000000000) -> 0.081432375 | Q8: =K8*Tasks!G6 -> 4286.475 | R8: =O8*Tasks!G6 -> 16286.475
A9: =Tasks!A6 -> T1 Support triage | B9: =Prices!A9 -> OpenAI | C9: =Prices!B9 -> Small | D9: =Prices!C9 -> gpt-6-luna | E9: =Tasks!C6*Prices!O9 -> 1500 | F9: =Tasks!D6*Prices!O9*Prices!P9 -> 300 | G9: =(E9*Prices!J9+F9*Prices!K9)/1000000 -> 0.0003 | H9: =(E9*(1-Tasks!E6)*Prices!J9+E9*Tasks!E6*(Tasks!F6*Prices!L9+(1-Tasks!F6)*Prices!J9*Prices!M9)+F9*Prices!K9)/1000000 -> 0.0002211075 | I9: =G9*(1-Prices!N9) -> 0.00015 | J9: =H9*(1-Prices!N9) -> 0.00011055375 | K9: =IF(Tasks!H6="Y",MIN(G9:J9),MIN(G9:H9)) -> 0.0002211075 | L9: =Quality!D9 -> 0.88 | M9: =IF(L9>=Tasks!J6,"Yes","No") -> No | N9: =IF(L9>0,K9/L9,0) -> 0.00025125852 | O9: =K9+(1-L9)*Tasks!I6 -> 0.24022111 | P9: =IF(M9="Yes",O9,1000000000) -> 1000000000 | Q9: =K9*Tasks!G6 -> 44.2215 | R9: =O9*Tasks!G6 -> 48044.221
A10: =Tasks!A6 -> T1 Support triage | B10: =Prices!A10 -> OpenAI | C10: =Prices!B10 -> Mid | D10: =Prices!C10 -> gpt-6.1-sol | E10: =Tasks!C6*Prices!O10 -> 1500 | F10: =Tasks!D6*Prices!O10*Prices!P10 -> 300 | G10: =(E10*Prices!J10+F10*Prices!K10)/1000000 -> 0.006 | H10: =(E10*(1-Tasks!E6)*Prices!J10+E10*Tasks!E6*(Tasks!F6*Prices!L10+(1-Tasks!F6)*Prices!J10*Prices!M10)+F10*Prices!K10)/1000000 -> 0.0043317 | I10: =G10*(1-Prices!N10) -> 0.003 | J10: =H10*(1-Prices!N10) -> 0.00216585 | K10: =IF(Tasks!H6="Y",MIN(G10:J10),MIN(G10:H10)) -> 0.0043317 | L10: =Quality!D10 -> 0.95 | M10: =IF(L10>=Tasks!J6,"Yes","No") -> Yes | N10: =IF(L10>0,K10/L10,0) -> 0.0045596842 | O10: =K10+(1-L10)*Tasks!I6 -> 0.1043317 | P10: =IF(M10="Yes",O10,1000000000) -> 0.1043317 | Q10: =K10*Tasks!G6 -> 866.34 | R10: =O10*Tasks!G6 -> 20866.34
A11: =Tasks!A6 -> T1 Support triage | B11: =Prices!A11 -> OpenAI | C11: =Prices!B11 -> Flagship | D11: =Prices!C11 -> gpt-6-astra | E11: =Tasks!C6*Prices!O11 -> 1500 | F11: =Tasks!D6*Prices!O11*Prices!P11 -> 300 | G11: =(E11*Prices!J11+F11*Prices!K11)/1000000 -> 0.03 | H11: =(E11*(1-Tasks!E6)*Prices!J11+E11*Tasks!E6*(Tasks!F6*Prices!L11+(1-Tasks!F6)*Prices!J11*Prices!M11)+F11*Prices!K11)/1000000 -> 0.02211075 | I11: =G11*(1-Prices!N11) -> 0.015 | J11: =H11*(1-Prices!N11) -> 0.011055375 | K11: =IF(Tasks!H6="Y",MIN(G11:J11),MIN(G11:H11)) -> 0.02211075 | L11: =Quality!D11 -> 0.97 | M11: =IF(L11>=Tasks!J6,"Yes","No") -> Yes | N11: =IF(L11>0,K11/L11,0) -> 0.022794588 | O11: =K11+(1-L11)*Tasks!I6 -> 0.08211075 | P11: =IF(M11="Yes",O11,1000000000) -> 0.08211075 | Q11: =K11*Tasks!G6 -> 4422.15 | R11: =O11*Tasks!G6 -> 16422.15
A12: =Tasks!A6 -> T1 Support triage | B12: =Prices!A12 -> Google | C12: =Prices!B12 -> Small | D12: =Prices!C12 -> Gemini 3.5 Flash-Lite | E12: =Tasks!C6*Prices!O12 -> 1500 | F12: =Tasks!D6*Prices!O12*Prices!P12 -> 300 | G12: =(E12*Prices!J12+F12*Prices!K12)/1000000 -> 0.0012 | H12: =(E12*(1-Tasks!E6)*Prices!J12+E12*Tasks!E6*(Tasks!F6*Prices!L12+(1-Tasks!F6)*Prices!J12*Prices!M12)+F12*Prices!K12)/1000000 -> 0.000955785 | I12: =G12*(1-Prices!N12) -> 0.0006 | J12: =H12*(1-Prices!N12) -> 0.0004778925 | K12: =IF(Tasks!H6="Y",MIN(G12:J12),MIN(G12:H12)) -> 0.000955785 | L12: =Quality!D12 -> 0.88 | M12: =IF(L12>=Tasks!J6,"Yes","No") -> No | N12: =IF(L12>0,K12/L12,0) -> 0.0010861193 | O12: =K12+(1-L12)*Tasks!I6 -> 0.24095579 | P12: =IF(M12="Yes",O12,1000000000) -> 1000000000 | Q12: =K12*Tasks!G6 -> 191.157 | R12: =O12*Tasks!G6 -> 48191.157
A13: =Tasks!A6 -> T1 Support triage | B13: =Prices!A13 -> Google | C13: =Prices!B13 -> Mid | D13: =Prices!C13 -> Gemini 3.8 Flash | E13: =Tasks!C6*Prices!O13 -> 1500 | F13: =Tasks!D6*Prices!O13*Prices!P13 -> 300 | G13: =(E13*Prices!J13+F13*Prices!K13)/1000000 -> 0.00225 | H13: =(E13*(1-Tasks!E6)*Prices!J13+E13*Tasks!E6*(Tasks!F6*Prices!L13+(1-Tasks!F6)*Prices!J13*Prices!M13)+F13*Prices!K13)/1000000 -> 0.0016394625 | I13: =G13*(1-Prices!N13) -> 0.001125 | J13: =H13*(1-Prices!N13) -> 0.00081973125 | K13: =IF(Tasks!H6="Y",MIN(G13:J13),MIN(G13:H13)) -> 0.0016394625 | L13: =Quality!D13 -> 0.95 | M13: =IF(L13>=Tasks!J6,"Yes","No") -> Yes | N13: =IF(L13>0,K13/L13,0) -> 0.00172575 | O13: =K13+(1-L13)*Tasks!I6 -> 0.10163946 | P13: =IF(M13="Yes",O13,1000000000) -> 0.10163946 | Q13: =K13*Tasks!G6 -> 327.8925 | R13: =O13*Tasks!G6 -> 20327.893
A14: =Tasks!A6 -> T1 Support triage | B14: =Prices!A14 -> Google | C14: =Prices!B14 -> Flagship | D14: =Prices!C14 -> Gemini 4 Argon | E14: =Tasks!C6*Prices!O14 -> 1500 | F14: =Tasks!D6*Prices!O14*Prices!P14 -> 300 | G14: =(E14*Prices!J14+F14*Prices!K14)/1000000 -> 0.006 | H14: =(E14*(1-Tasks!E6)*Prices!J14+E14*Tasks!E6*(Tasks!F6*Prices!L14+(1-Tasks!F6)*Prices!J14*Prices!M14)+F14*Prices!K14)/1000000 -> 0.00428145 | I14: =G14*(1-Prices!N14) -> 0.003 | J14: =H14*(1-Prices!N14) -> 0.002140725 | K14: =IF(Tasks!H6="Y",MIN(G14:J14),MIN(G14:H14)) -> 0.00428145 | L14: =Quality!D14 -> 0.97 | M14: =IF(L14>=Tasks!J6,"Yes","No") -> Yes | N14: =IF(L14>0,K14/L14,0) -> 0.004413866 | O14: =K14+(1-L14)*Tasks!I6 -> 0.06428145 | P14: =IF(M14="Yes",O14,1000000000) -> 0.06428145 | Q14: =K14*Tasks!G6 -> 856.29 | R14: =O14*Tasks!G6 -> 12856.29
A15: =Tasks!A7 -> T2 Document summary | B15: =Prices!A6 -> Anthropic | C15: =Prices!B6 -> Small | D15: =Prices!C6 -> Claude Haiku 5.5 | E15: =Tasks!C7*Prices!O6 -> 20000 | F15: =Tasks!D7*Prices!O6*Prices!P6 -> 800 | G15: =(E15*Prices!J6+F15*Prices!K6)/1000000 -> 0.0024 | H15: =(E15*(1-Tasks!E7)*Prices!J6+E15*Tasks!E7*(Tasks!F7*Prices!L6+(1-Tasks!F7)*Prices!J6*Prices!M6)+F15*Prices!K6)/1000000 -> 0.002335 | I15: =G15*(1-Prices!N6) -> 0.0012 | J15: =H15*(1-Prices!N6) -> 0.0011675 | K15: =IF(Tasks!H7="Y",MIN(G15:J15),MIN(G15:H15)) -> 0.0011675 | L15: =Quality!E6 -> 0.8 | M15: =IF(L15>=Tasks!J7,"Yes","No") -> No | N15: =IF(L15>0,K15/L15,0) -> 0.001459375 | O15: =K15+(1-L15)*Tasks!I7 -> 1.6011675 | P15: =IF(M15="Yes",O15,1000000000) -> 1000000000 | Q15: =K15*Tasks!G7 -> 5.8375 | R15: =O15*Tasks!G7 -> 8005.8375
A16: =Tasks!A7 -> T2 Document summary | B16: =Prices!A7 -> Anthropic | C16: =Prices!B7 -> Mid | D16: =Prices!C7 -> Claude Sonnet 5.5 | E16: =Tasks!C7*Prices!O7 -> 20000 | F16: =Tasks!D7*Prices!O7*Prices!P7 -> 800 | G16: =(E16*Prices!J7+F16*Prices!K7)/1000000 -> 0.048 | H16: =(E16*(1-Tasks!E7)*Prices!J7+E16*Tasks!E7*(Tasks!F7*Prices!L7+(1-Tasks!F7)*Prices!J7*Prices!M7)+F16*Prices!K7)/1000000 -> 0.0466 | I16: =G16*(1-Prices!N7) -> 0.024 | J16: =H16*(1-Prices!N7) -> 0.0233 | K16: =IF(Tasks!H7="Y",MIN(G16:J16),MIN(G16:H16)) -> 0.0233 | L16: =Quality!E7 -> 0.92 | M16: =IF(L16>=Tasks!J7,"Yes","No") -> Yes | N16: =IF(L16>0,K16/L16,0) -> 0.025326087 | O16: =K16+(1-L16)*Tasks!I7 -> 0.6633 | P16: =IF(M16="Yes",O16,1000000000) -> 0.6633 | Q16: =K16*Tasks!G7 -> 116.5 | R16: =O16*Tasks!G7 -> 3316.5
A17: =Tasks!A7 -> T2 Document summary | B17: =Prices!A8 -> Anthropic | C17: =Prices!B8 -> Flagship | D17: =Prices!C8 -> Claude Fable 5.1 | E17: =Tasks!C7*Prices!O8 -> 20000 | F17: =Tasks!D7*Prices!O8*Prices!P8 -> 800 | G17: =(E17*Prices!J8+F17*Prices!K8)/1000000 -> 0.24 | H17: =(E17*(1-Tasks!E7)*Prices!J8+E17*Tasks!E7*(Tasks!F7*Prices!L8+(1-Tasks!F7)*Prices!J8*Prices!M8)+F17*Prices!K8)/1000000 -> 0.23275 | I17: =G17*(1-Prices!N8) -> 0.12 | J17: =H17*(1-Prices!N8) -> 0.116375 | K17: =IF(Tasks!H7="Y",MIN(G17:J17),MIN(G17:H17)) -> 0.116375 | L17: =Quality!E8 -> 0.95 | M17: =IF(L17>=Tasks!J7,"Yes","No") -> Yes | N17: =IF(L17>0,K17/L17,0) -> 0.1225 | O17: =K17+(1-L17)*Tasks!I7 -> 0.516375 | P17: =IF(M17="Yes",O17,1000000000) -> 0.516375 | Q17: =K17*Tasks!G7 -> 581.875 | R17: =O17*Tasks!G7 -> 2581.875
A18: =Tasks!A7 -> T2 Document summary | B18: =Prices!A9 -> OpenAI | C18: =Prices!B9 -> Small | D18: =Prices!C9 -> gpt-6-luna | E18: =Tasks!C7*Prices!O9 -> 20000 | F18: =Tasks!D7*Prices!O9*Prices!P9 -> 800 | G18: =(E18*Prices!J9+F18*Prices!K9)/1000000 -> 0.0024 | H18: =(E18*(1-Tasks!E7)*Prices!J9+E18*Tasks!E7*(Tasks!F7*Prices!L9+(1-Tasks!F7)*Prices!J9*Prices!M9)+F18*Prices!K9)/1000000 -> 0.002335 | I18: =G18*(1-Prices!N9) -> 0.0012 | J18: =H18*(1-Prices!N9) -> 0.0011675 | K18: =IF(Tasks!H7="Y",MIN(G18:J18),MIN(G18:H18)) -> 0.0011675 | L18: =Quality!E9 -> 0.8 | M18: =IF(L18>=Tasks!J7,"Yes","No") -> No | N18: =IF(L18>0,K18/L18,0) -> 0.001459375 | O18: =K18+(1-L18)*Tasks!I7 -> 1.6011675 | P18: =IF(M18="Yes",O18,1000000000) -> 1000000000 | Q18: =K18*Tasks!G7 -> 5.8375 | R18: =O18*Tasks!G7 -> 8005.8375
A19: =Tasks!A7 -> T2 Document summary | B19: =Prices!A10 -> OpenAI | C19: =Prices!B10 -> Mid | D19: =Prices!C10 -> gpt-6.1-sol | E19: =Tasks!C7*Prices!O10 -> 20000 | F19: =Tasks!D7*Prices!O10*Prices!P10 -> 800 | G19: =(E19*Prices!J10+F19*Prices!K10)/1000000 -> 0.048 | H19: =(E19*(1-Tasks!E7)*Prices!J10+E19*Tasks!E7*(Tasks!F7*Prices!L10+(1-Tasks!F7)*Prices!J10*Prices!M10)+F19*Prices!K10)/1000000 -> 0.0466 | I19: =G19*(1-Prices!N10) -> 0.024 | J19: =H19*(1-Prices!N10) -> 0.0233 | K19: =IF(Tasks!H7="Y",MIN(G19:J19),MIN(G19:H19)) -> 0.0233 | L19: =Quality!E10 -> 0.92 | M19: =IF(L19>=Tasks!J7,"Yes","No") -> Yes | N19: =IF(L19>0,K19/L19,0) -> 0.025326087 | O19: =K19+(1-L19)*Tasks!I7 -> 0.6633 | P19: =IF(M19="Yes",O19,1000000000) -> 0.6633 | Q19: =K19*Tasks!G7 -> 116.5 | R19: =O19*Tasks!G7 -> 3316.5
A20: =Tasks!A7 -> T2 Document summary | B20: =Prices!A11 -> OpenAI | C20: =Prices!B11 -> Flagship | D20: =Prices!C11 -> gpt-6-astra | E20: =Tasks!C7*Prices!O11 -> 20000 | F20: =Tasks!D7*Prices!O11*Prices!P11 -> 800 | G20: =(E20*Prices!J11+F20*Prices!K11)/1000000 -> 0.24 | H20: =(E20*(1-Tasks!E7)*Prices!J11+E20*Tasks!E7*(Tasks!F7*Prices!L11+(1-Tasks!F7)*Prices!J11*Prices!M11)+F20*Prices!K11)/1000000 -> 0.2335 | I20: =G20*(1-Prices!N11) -> 0.12 | J20: =H20*(1-Prices!N11) -> 0.11675 | K20: =IF(Tasks!H7="Y",MIN(G20:J20),MIN(G20:H20)) -> 0.11675 | L20: =Quality!E11 -> 0.95 | M20: =IF(L20>=Tasks!J7,"Yes","No") -> Yes | N20: =IF(L20>0,K20/L20,0) -> 0.12289474 | O20: =K20+(1-L20)*Tasks!I7 -> 0.51675 | P20: =IF(M20="Yes",O20,1000000000) -> 0.51675 | Q20: =K20*Tasks!G7 -> 583.75 | R20: =O20*Tasks!G7 -> 2583.75
A21: =Tasks!A7 -> T2 Document summary | B21: =Prices!A12 -> Google | C21: =Prices!B12 -> Small | D21: =Prices!C12 -> Gemini 3.5 Flash-Lite | E21: =Tasks!C7*Prices!O12 -> 20000 | F21: =Tasks!D7*Prices!O12*Prices!P12 -> 800 | G21: =(E21*Prices!J12+F21*Prices!K12)/1000000 -> 0.008 | H21: =(E21*(1-Tasks!E7)*Prices!J12+E21*Tasks!E7*(Tasks!F7*Prices!L12+(1-Tasks!F7)*Prices!J12*Prices!M12)+F21*Prices!K12)/1000000 -> 0.00773 | I21: =G21*(1-Prices!N12) -> 0.004 | J21: =H21*(1-Prices!N12) -> 0.003865 | K21: =IF(Tasks!H7="Y",MIN(G21:J21),MIN(G21:H21)) -> 0.003865 | L21: =Quality!E12 -> 0.8 | M21: =IF(L21>=Tasks!J7,"Yes","No") -> No | N21: =IF(L21>0,K21/L21,0) -> 0.00483125 | O21: =K21+(1-L21)*Tasks!I7 -> 1.603865 | P21: =IF(M21="Yes",O21,1000000000) -> 1000000000 | Q21: =K21*Tasks!G7 -> 19.325 | R21: =O21*Tasks!G7 -> 8019.325
A22: =Tasks!A7 -> T2 Document summary | B22: =Prices!A13 -> Google | C22: =Prices!B13 -> Mid | D22: =Prices!C13 -> Gemini 3.8 Flash | E22: =Tasks!C7*Prices!O13 -> 20000 | F22: =Tasks!D7*Prices!O13*Prices!P13 -> 800 | G22: =(E22*Prices!J13+F22*Prices!K13)/1000000 -> 0.018 | H22: =(E22*(1-Tasks!E7)*Prices!J13+E22*Tasks!E7*(Tasks!F7*Prices!L13+(1-Tasks!F7)*Prices!J13*Prices!M13)+F22*Prices!K13)/1000000 -> 0.017325 | I22: =G22*(1-Prices!N13) -> 0.009 | J22: =H22*(1-Prices!N13) -> 0.0086625 | K22: =IF(Tasks!H7="Y",MIN(G22:J22),MIN(G22:H22)) -> 0.0086625 | L22: =Quality!E13 -> 0.92 | M22: =IF(L22>=Tasks!J7,"Yes","No") -> Yes | N22: =IF(L22>0,K22/L22,0) -> 0.0094157609 | O22: =K22+(1-L22)*Tasks!I7 -> 0.6486625 | P22: =IF(M22="Yes",O22,1000000000) -> 0.6486625 | Q22: =K22*Tasks!G7 -> 43.3125 | R22: =O22*Tasks!G7 -> 3243.3125
A23: =Tasks!A7 -> T2 Document summary | B23: =Prices!A14 -> Google | C23: =Prices!B14 -> Flagship | D23: =Prices!C14 -> Gemini 4 Argon | E23: =Tasks!C7*Prices!O14 -> 20000 | F23: =Tasks!D7*Prices!O14*Prices!P14 -> 800 | G23: =(E23*Prices!J14+F23*Prices!K14)/1000000 -> 0.048 | H23: =(E23*(1-Tasks!E7)*Prices!J14+E23*Tasks!E7*(Tasks!F7*Prices!L14+(1-Tasks!F7)*Prices!J14*Prices!M14)+F23*Prices!K14)/1000000 -> 0.0461 | I23: =G23*(1-Prices!N14) -> 0.024 | J23: =H23*(1-Prices!N14) -> 0.02305 | K23: =IF(Tasks!H7="Y",MIN(G23:J23),MIN(G23:H23)) -> 0.02305 | L23: =Quality!E14 -> 0.95 | M23: =IF(L23>=Tasks!J7,"Yes","No") -> Yes | N23: =IF(L23>0,K23/L23,0) -> 0.024263158 | O23: =K23+(1-L23)*Tasks!I7 -> 0.42305 | P23: =IF(M23="Yes",O23,1000000000) -> 0.42305 | Q23: =K23*Tasks!G7 -> 115.25 | R23: =O23*Tasks!G7 -> 2115.25
A24: =Tasks!A8 -> T3 Complex analysis | B24: =Prices!A6 -> Anthropic | C24: =Prices!B6 -> Small | D24: =Prices!C6 -> Claude Haiku 5.5 | E24: =Tasks!C8*Prices!O6 -> 40000 | F24: =Tasks!D8*Prices!O6*Prices!P6 -> 6000 | G24: =(E24*Prices!J6+F24*Prices!K6)/1000000 -> 0.007 | H24: =(E24*(1-Tasks!E8)*Prices!J6+E24*Tasks!E8*(Tasks!F8*Prices!L6+(1-Tasks!F8)*Prices!J6*Prices!M6)+F24*Prices!K6)/1000000 -> 0.005446 | I24: =G24*(1-Prices!N6) -> 0.0035 | J24: =H24*(1-Prices!N6) -> 0.002723 | K24: =IF(Tasks!H8="Y",MIN(G24:J24),MIN(G24:H24)) -> 0.005446 | L24: =Quality!F6 -> 0.35 | M24: =IF(L24>=Tasks!J8,"Yes","No") -> No | N24: =IF(L24>0,K24/L24,0) -> 0.01556 | O24: =K24+(1-L24)*Tasks!I8 -> 26.005446 | P24: =IF(M24="Yes",O24,1000000000) -> 1000000000 | Q24: =K24*Tasks!G8 -> 5.446 | R24: =O24*Tasks!G8 -> 26005.446
A25: =Tasks!A8 -> T3 Complex analysis | B25: =Prices!A7 -> Anthropic | C25: =Prices!B7 -> Mid | D25: =Prices!C7 -> Claude Sonnet 5.5 | E25: =Tasks!C8*Prices!O7 -> 40000 | F25: =Tasks!D8*Prices!O7*Prices!P7 -> 6000 | G25: =(E25*Prices!J7+F25*Prices!K7)/1000000 -> 0.14 | H25: =(E25*(1-Tasks!E8)*Prices!J7+E25*Tasks!E8*(Tasks!F8*Prices!L7+(1-Tasks!F8)*Prices!J7*Prices!M7)+F25*Prices!K7)/1000000 -> 0.10696 | I25: =G25*(1-Prices!N7) -> 0.07 | J25: =H25*(1-Prices!N7) -> 0.05348 | K25: =IF(Tasks!H8="Y",MIN(G25:J25),MIN(G25:H25)) -> 0.10696 | L25: =Quality!F7 -> 0.7 | M25: =IF(L25>=Tasks!J8,"Yes","No") -> No | N25: =IF(L25>0,K25/L25,0) -> 0.1528 | O25: =K25+(1-L25)*Tasks!I8 -> 12.10696 | P25: =IF(M25="Yes",O25,1000000000) -> 1000000000 | Q25: =K25*Tasks!G8 -> 106.96 | R25: =O25*Tasks!G8 -> 12106.96
A26: =Tasks!A8 -> T3 Complex analysis | B26: =Prices!A8 -> Anthropic | C26: =Prices!B8 -> Flagship | D26: =Prices!C8 -> Claude Fable 5.1 | E26: =Tasks!C8*Prices!O8 -> 40000 | F26: =Tasks!D8*Prices!O8*Prices!P8 -> 6000 | G26: =(E26*Prices!J8+F26*Prices!K8)/1000000 -> 0.7 | H26: =(E26*(1-Tasks!E8)*Prices!J8+E26*Tasks!E8*(Tasks!F8*Prices!L8+(1-Tasks!F8)*Prices!J8*Prices!M8)+F26*Prices!K8)/1000000 -> 0.5299 | I26: =G26*(1-Prices!N8) -> 0.35 | J26: =H26*(1-Prices!N8) -> 0.26495 | K26: =IF(Tasks!H8="Y",MIN(G26:J26),MIN(G26:H26)) -> 0.5299 | L26: =Quality!F8 -> 0.88 | M26: =IF(L26>=Tasks!J8,"Yes","No") -> Yes | N26: =IF(L26>0,K26/L26,0) -> 0.60215909 | O26: =K26+(1-L26)*Tasks!I8 -> 5.3299 | P26: =IF(M26="Yes",O26,1000000000) -> 5.3299 | Q26: =K26*Tasks!G8 -> 529.9 | R26: =O26*Tasks!G8 -> 5329.9
A27: =Tasks!A8 -> T3 Complex analysis | B27: =Prices!A9 -> OpenAI | C27: =Prices!B9 -> Small | D27: =Prices!C9 -> gpt-6-luna | E27: =Tasks!C8*Prices!O9 -> 40000 | F27: =Tasks!D8*Prices!O9*Prices!P9 -> 6000 | G27: =(E27*Prices!J9+F27*Prices!K9)/1000000 -> 0.007 | H27: =(E27*(1-Tasks!E8)*Prices!J9+E27*Tasks!E8*(Tasks!F8*Prices!L9+(1-Tasks!F8)*Prices!J9*Prices!M9)+F27*Prices!K9)/1000000 -> 0.005446 | I27: =G27*(1-Prices!N9) -> 0.0035 | J27: =H27*(1-Prices!N9) -> 0.002723 | K27: =IF(Tasks!H8="Y",MIN(G27:J27),MIN(G27:H27)) -> 0.005446 | L27: =Quality!F9 -> 0.35 | M27: =IF(L27>=Tasks!J8,"Yes","No") -> No | N27: =IF(L27>0,K27/L27,0) -> 0.01556 | O27: =K27+(1-L27)*Tasks!I8 -> 26.005446 | P27: =IF(M27="Yes",O27,1000000000) -> 1000000000 | Q27: =K27*Tasks!G8 -> 5.446 | R27: =O27*Tasks!G8 -> 26005.446
A28: =Tasks!A8 -> T3 Complex analysis | B28: =Prices!A10 -> OpenAI | C28: =Prices!B10 -> Mid | D28: =Prices!C10 -> gpt-6.1-sol | E28: =Tasks!C8*Prices!O10 -> 40000 | F28: =Tasks!D8*Prices!O10*Prices!P10 -> 6000 | G28: =(E28*Prices!J10+F28*Prices!K10)/1000000 -> 0.14 | H28: =(E28*(1-Tasks!E8)*Prices!J10+E28*Tasks!E8*(Tasks!F8*Prices!L10+(1-Tasks!F8)*Prices!J10*Prices!M10)+F28*Prices!K10)/1000000 -> 0.10696 | I28: =G28*(1-Prices!N10) -> 0.07 | J28: =H28*(1-Prices!N10) -> 0.05348 | K28: =IF(Tasks!H8="Y",MIN(G28:J28),MIN(G28:H28)) -> 0.10696 | L28: =Quality!F10 -> 0.7 | M28: =IF(L28>=Tasks!J8,"Yes","No") -> No | N28: =IF(L28>0,K28/L28,0) -> 0.1528 | O28: =K28+(1-L28)*Tasks!I8 -> 12.10696 | P28: =IF(M28="Yes",O28,1000000000) -> 1000000000 | Q28: =K28*Tasks!G8 -> 106.96 | R28: =O28*Tasks!G8 -> 12106.96
A29: =Tasks!A8 -> T3 Complex analysis | B29: =Prices!A11 -> OpenAI | C29: =Prices!B11 -> Flagship | D29: =Prices!C11 -> gpt-6-astra | E29: =Tasks!C8*Prices!O11 -> 40000 | F29: =Tasks!D8*Prices!O11*Prices!P11 -> 6000 | G29: =(E29*Prices!J11+F29*Prices!K11)/1000000 -> 0.7 | H29: =(E29*(1-Tasks!E8)*Prices!J11+E29*Tasks!E8*(Tasks!F8*Prices!L11+(1-Tasks!F8)*Prices!J11*Prices!M11)+F29*Prices!K11)/1000000 -> 0.5446 | I29: =G29*(1-Prices!N11) -> 0.35 | J29: =H29*(1-Prices!N11) -> 0.2723 | K29: =IF(Tasks!H8="Y",MIN(G29:J29),MIN(G29:H29)) -> 0.5446 | L29: =Quality!F11 -> 0.88 | M29: =IF(L29>=Tasks!J8,"Yes","No") -> Yes | N29: =IF(L29>0,K29/L29,0) -> 0.61886364 | O29: =K29+(1-L29)*Tasks!I8 -> 5.3446 | P29: =IF(M29="Yes",O29,1000000000) -> 5.3446 | Q29: =K29*Tasks!G8 -> 544.6 | R29: =O29*Tasks!G8 -> 5344.6
A30: =Tasks!A8 -> T3 Complex analysis | B30: =Prices!A12 -> Google | C30: =Prices!B12 -> Small | D30: =Prices!C12 -> Gemini 3.5 Flash-Lite | E30: =Tasks!C8*Prices!O12 -> 40000 | F30: =Tasks!D8*Prices!O12*Prices!P12 -> 6000 | G30: =(E30*Prices!J12+F30*Prices!K12)/1000000 -> 0.027 | H30: =(E30*(1-Tasks!E8)*Prices!J12+E30*Tasks!E8*(Tasks!F8*Prices!L12+(1-Tasks!F8)*Prices!J12*Prices!M12)+F30*Prices!K12)/1000000 -> 0.021708 | I30: =G30*(1-Prices!N12) -> 0.0135 | J30: =H30*(1-Prices!N12) -> 0.010854 | K30: =IF(Tasks!H8="Y",MIN(G30:J30),MIN(G30:H30)) -> 0.021708 | L30: =Quality!F12 -> 0.35 | M30: =IF(L30>=Tasks!J8,"Yes","No") -> No | N30: =IF(L30>0,K30/L30,0) -> 0.062022857 | O30: =K30+(1-L30)*Tasks!I8 -> 26.021708 | P30: =IF(M30="Yes",O30,1000000000) -> 1000000000 | Q30: =K30*Tasks!G8 -> 21.708 | R30: =O30*Tasks!G8 -> 26021.708
A31: =Tasks!A8 -> T3 Complex analysis | B31: =Prices!A13 -> Google | C31: =Prices!B13 -> Mid | D31: =Prices!C13 -> Gemini 3.8 Flash | E31: =Tasks!C8*Prices!O13 -> 40000 | F31: =Tasks!D8*Prices!O13*Prices!P13 -> 6000 | G31: =(E31*Prices!J13+F31*Prices!K13)/1000000 -> 0.0525 | H31: =(E31*(1-Tasks!E8)*Prices!J13+E31*Tasks!E8*(Tasks!F8*Prices!L13+(1-Tasks!F8)*Prices!J13*Prices!M13)+F31*Prices!K13)/1000000 -> 0.03927 | I31: =G31*(1-Prices!N13) -> 0.02625 | J31: =H31*(1-Prices!N13) -> 0.019635 | K31: =IF(Tasks!H8="Y",MIN(G31:J31),MIN(G31:H31)) -> 0.03927 | L31: =Quality!F13 -> 0.7 | M31: =IF(L31>=Tasks!J8,"Yes","No") -> No | N31: =IF(L31>0,K31/L31,0) -> 0.0561 | O31: =K31+(1-L31)*Tasks!I8 -> 12.03927 | P31: =IF(M31="Yes",O31,1000000000) -> 1000000000 | Q31: =K31*Tasks!G8 -> 39.27 | R31: =O31*Tasks!G8 -> 12039.27
A32: =Tasks!A8 -> T3 Complex analysis | B32: =Prices!A14 -> Google | C32: =Prices!B14 -> Flagship | D32: =Prices!C14 -> Gemini 4 Argon | E32: =Tasks!C8*Prices!O14 -> 40000 | F32: =Tasks!D8*Prices!O14*Prices!P14 -> 6000 | G32: =(E32*Prices!J14+F32*Prices!K14)/1000000 -> 0.14 | H32: =(E32*(1-Tasks!E8)*Prices!J14+E32*Tasks!E8*(Tasks!F8*Prices!L14+(1-Tasks!F8)*Prices!J14*Prices!M14)+F32*Prices!K14)/1000000 -> 0.10276 | I32: =G32*(1-Prices!N14) -> 0.07 | J32: =H32*(1-Prices!N14) -> 0.05138 | K32: =IF(Tasks!H8="Y",MIN(G32:J32),MIN(G32:H32)) -> 0.10276 | L32: =Quality!F14 -> 0.88 | M32: =IF(L32>=Tasks!J8,"Yes","No") -> Yes | N32: =IF(L32>0,K32/L32,0) -> 0.11677273 | O32: =K32+(1-L32)*Tasks!I8 -> 4.90276 | P32: =IF(M32="Yes",O32,1000000000) -> 4.90276 | Q32: =K32*Tasks!G8 -> 102.76 | R32: =O32*Tasks!G8 -> 4902.76
